addrcollector.py
addrcollector-2.0.0.dist-info/entry_points.txt
addrcollector-2.0.0.dist-info/LICENSE
addrcollector-2.0.0.dist-info/WHEEL
addrcollector-2.0.0.dist-info/METADATA
addrcollector-2.0.0.dist-info/RECORD
