Metadata-Version: 2.1
Name: addrcollector
Version: 2.0.0
Summary: A Python application for collecting email addresses from email messages
Home-page: https://owenh.net/addrcollector
License: CC0-1.0
Keywords: email
Author: Owen T. Heisler
Author-email: writer@owenh.net
Requires-Python: >=3.6,<4.0
Classifier: Development Status :: 5 - Production/Stable
Classifier: Environment :: Console
Classifier: Intended Audience :: End Users/Desktop
Classifier: License :: CC0 1.0 Universal (CC0 1.0) Public Domain Dedication
Classifier: Natural Language :: English
Classifier: Programming Language :: Python :: 3
Classifier: Programming Language :: Python :: 3.6
Classifier: Programming Language :: Python :: 3.7
Classifier: Programming Language :: Python :: 3.8
Classifier: Topic :: Communications :: Email :: Address Book
Project-URL: Repository, https://github.com/owenh000/addrcollector
